famqy/__init__.py
famqy/funcs.py
famqy/utils.py
famqy-0.1.1.dist-info/METADATA
famqy-0.1.1.dist-info/WHEEL
famqy-0.1.1.dist-info/top_level.txt
famqy-0.1.1.dist-info/RECORD
